{
  "pick_status": "unprocessed",
  "pick_id": "Boston_Celtics_2026_2",
  "year": 2026,
  "round": 2,
  "original_team": "Boston Celtics",
  "frozen": false,
  "rules": {
    "type": "nested_swap",
    "possible_destinations": [
      "Atlanta Hawks",
      "Utah Jazz",
      "Cleveland Cavaliers"
    ],
    "levels": [
      {
        "description": "Sub-swap (ii): less favorable of UTH and CLE",
        "pool": [
          "Utah_Jazz_2028_1",
          "Cleveland_Cavaliers_2028_1"
        ],
        "allocation": [
          { "rank": "mf", "to": "Utah Jazz" },
          { "rank": "lf", "to": "TEMP_II_LF" }
        ]
      },
      {
        "description": "More favorable of ATL and (lf of UTH and CLE)",
        "pool": [
          "Atlanta_Hawks_2028_1",
          "TEMP_II_LF"
        ],
        "allocation": [
          { "rank": "mf", "to": "Atlanta Hawks" },
          { "rank": "lf", "to": "Cleveland Cavaliers" }
        ]
      }
    ]
  }
}
{
  "pick_status": "unprocessed",
  "pick_id": "Boston_Celtics_2026_2",
  "year": 2026,
  "round": 2,
  "original_team": "Boston Celtics",
  "frozen": false,
  "rules": {
    "type": "nested_swap",
    "possible_destinations": [
      "Atlanta Hawks",
      "Memphis Grizzlies",
      "Brooklyn Nets"
    ],
    "levels": [
      {
        "description": "MF of IND and MIA",
        "pool": [
          "Indiana_Pacers_2026_2",
          "Miami_Heat_2026_2"
        ],
        "allocation": [
          { "rank": "mf", "to": "TEMP_IND_MIA_MF" },
          { "rank": "lf", "to": "TEMP_IND_MIA_LF" }
        ]
      },
      {
        "description": "MF of (BOS, MF(IND,MIA)) to TEMP, LF to ATL",
        "pool": [
          "Boston_Celtics_2026_2",
          "TEMP_IND_MIA_MF"
        ],
        "allocation": [
          { "rank": "mf", "to": "TEMP_BEST" },
          { "rank": "lf", "to": "Atlanta Hawks" }
        ]
      },
      {
        "description": "MEM keeps MF of (TEMP_BEST, LAC), LF to BKN",
        "pool": [
          "TEMP_BEST",
          "LA_Clippers_2026_2"
        ],
        "allocation": [
          { "rank": "mf", "to": "Memphis Grizzlies" },
          { "rank": "lf", "to": "Brooklyn Nets" }
        ]
      }
    ]
  }
}