{
  "pick_status": "processed",
  "pick_id": "Houston_Rockets_2031_2",
  "year": 2031,
  "round": 2,
  "original_team": "Houston Rockets",
  "frozen": false,
  "rules": {
    "type": "protected_swap",
    "possible_destinations": ["Houston Rockets", "Atlanta Hawks", "Boston Celtics"],
    "pool": [
      "Atlanta_Hawks_2031_2",
      {"pick": "Houston_Rockets_2031_2", "condition": {"range": [31, 55]}}
    ],
    "if_protected_to": "Boston Celtics",
    "allocation": [
      {"rank": "mf", "to": "Atlanta Hawks"},
      {"rank": "lf", "to": "Houston Rockets"}
    ]
  }
}