{
  "pick_status": "processed",
  "pick_id": "Milwaukee_Bucks_2030_1",
  "year": 2030,
  "round": 1,
  "original_team": "Milwaukee Bucks",
  "frozen": false,
  "rules": {
    "type": "unpro_swap",
    "swap_id": "unpro_swap_301milpor",
    "possible_destinations": ["Milwaukee Bucks", "Portland Trail Blazers"],
    "pool": ["Milwaukee_Bucks_2030_1", "Portland_Trail_Blazers_2030_1"],
    "allocation": [
      {"rank": "1", "to": "Portland Trail Blazers"},
      {"rank": "2", "to": "Milwaukee Bucks"}
    ]
  }
}